data_reader/__init__.py
data_reader/mapper.py
data_reader/readers/__init__.py
data_reader/readers/csv_reader.py
data_reader/readers/json_reader.py
data_reader/readers/xml_reader.py
data_reader/utils/__init__.py
data_reader/utils/accessor.py
data_reader/utils/logger.py
data_reader-0.0.8.dist-info/METADATA
data_reader-0.0.8.dist-info/WHEEL
data_reader-0.0.8.dist-info/top_level.txt
data_reader-0.0.8.dist-info/RECORD
