Metadata-Version: 2.1
Name: data-reader
Version: 0.0.8
Summary: Lightweight Python package that can lazily read large data files.
Home-page: https://github.com/polkovnik-z/python-data-reader
Author: Ibragim Abubakarov
Author-email: ibragim.ai95@gmail.com
Maintainer: Ibragim Abubakarov
Maintainer-email: ibragim.ai95@gmail.com
License: MIT
Platform: UNKNOWN
Classifier: Programming Language :: Python :: 3
Classifier: Operating System :: OS Independent
Classifier: Intended Audience :: Developers
Classifier: Topic :: Software Development :: Libraries :: Python Modules
Requires-Dist: ijson
